tests/__init__.py
tests/conftest.py
tests/i9n/__init__.py
tests/i9n/test_acronym_route_name.py
tests/i9n/test_allow_anon.py
tests/i9n/test_apikey_generation.py
tests/i9n/test_authn_provider_integration.py
tests/i9n/test_bindings_integration.py
tests/i9n/test_bindings_modules.py
tests/i9n/test_bulk_docs_client.py
tests/i9n/test_core_access.py
tests/i9n/test_error_mappings.py
tests/i9n/test_field_spec_effects.py
tests/i9n/test_header_io_uvicorn.py
tests/i9n/test_healthz_methodz_hookz.py
tests/i9n/test_hook_ctx_v3_i9n.py
tests/i9n/test_hook_lifecycle.py
tests/i9n/test_iospec_attributes.py
tests/i9n/test_iospec_integration.py
tests/i9n/test_key_digest_uvicorn.py
tests/i9n/test_list_filters_optional.py
tests/i9n/test_mixins.py
tests/i9n/test_nested_path_schema_and_rpc.py
tests/i9n/test_nested_routing_depth.py
tests/i9n/test_op_ctx_alias_examples.py
tests/i9n/test_op_ctx_behavior.py
tests/i9n/test_op_ctx_core_crud_order.py
tests/i9n/test_openapi_clear_response_schema.py
tests/i9n/test_openapi_schema_examples_presence.py
tests/i9n/test_opspec_effects_i9n_test.py
tests/i9n/test_owner_tenant_policy.py
tests/i9n/test_request_extras.py
tests/i9n/test_request_extras_provider.py
tests/i9n/test_response_extras_provider.py
tests/i9n/test_rest_fallback_serialization.py
tests/i9n/test_rest_row_serialization.py
tests/i9n/test_rest_rpc_parity_v3.py
tests/i9n/test_row_result_serialization.py
tests/i9n/test_schema.py
tests/i9n/test_schema_ctx_attributes_integration.py
tests/i9n/test_schema_ctx_op_ctx_integration.py
tests/i9n/test_schema_ctx_spec_integration.py
tests/i9n/test_sqlite_attachments.py
tests/i9n/test_storage_spec_integration.py
tests/i9n/test_symmetry_parity.py
tests/i9n/test_tigrbl_api_app_usage_uvicorn.py
tests/i9n/test_tigrbl_api_usage_uvicorn.py
tests/i9n/test_tigrbl_api_uvicorn.py
tests/i9n/test_tigrbl_app_include_api_uvicorn.py
tests/i9n/test_tigrbl_app_multi_api_uvicorn.py
tests/i9n/test_tigrbl_app_usage_uvicorn.py
tests/i9n/test_tigrbl_app_uvicorn.py
tigrbl_tests-0.3.3.dist-info/METADATA
tigrbl_tests-0.3.3.dist-info/WHEEL
tigrbl_tests-0.3.3.dist-info/licenses/LICENSE
tigrbl_tests-0.3.3.dist-info/RECORD
