Metadata-Version: 2.4
Name: tigrbl-tests
Version: 0.3.3
Summary: Test suite and fixtures for the Tigrbl framework.
License-Expression: Apache-2.0
License-File: LICENSE
Keywords: tigrbl,tests,sdk,standards,pytest,fixtures,integration,performance
Author: Jacob Stewart
Author-email: jacob@swarmauri.com
Requires-Python: >=3.10,<3.13
Classifier: Development Status :: 1 - Planning
Classifier: License :: OSI Approved :: Apache Software License
Classifier: Natural Language :: English
Classifier: Programming Language :: Python :: 3.10
Classifier: Programming Language :: Python :: 3.11
Classifier: Programming Language :: Python :: 3.12
Classifier: Programming Language :: Python
Classifier: Programming Language :: Python :: 3
Classifier: Programming Language :: Python :: 3 :: Only
Requires-Dist: asyncpg (>=0.30.0)
Requires-Dist: flake8 (>=7.0)
Requires-Dist: psycopg2-binary (>=2.9.9)
Requires-Dist: pytest (>=8.0)
Requires-Dist: pytest-asyncio (>=0.24.0)
Requires-Dist: pytest-benchmark (>=4.0.0)
Requires-Dist: pytest-json-report (>=1.5.0)
Requires-Dist: pytest-timeout (>=2.3.1)
Requires-Dist: pytest-xdist (>=3.6.1)
Requires-Dist: python-dotenv
Requires-Dist: requests (>=2.32.3)
Requires-Dist: ruff (>=0.9.9)
Requires-Dist: tigrbl
Requires-Dist: tigrbl_client
